ldproto/__init__.py
ldproto/delimited.py
ldproto-0.1.12.dist-info/LICENSE
ldproto-0.1.12.dist-info/WHEEL
ldproto-0.1.12.dist-info/METADATA
ldproto-0.1.12.dist-info/RECORD
