Metadata-Version: 2.1
Name: ldproto
Version: 0.1.12
Summary: 
Author: Sebastian Nyberg
Author-email: seb.nyberg90@gmail.com
Requires-Python: >=3.7,<4.0
Classifier: Programming Language :: Python :: 3
Classifier: Programming Language :: Python :: 3.7
Classifier: Programming Language :: Python :: 3.8
